xpublish_host/__init__.py
xpublish_host/_version.py
xpublish_host/app.py
xpublish_host/config.py
xpublish_host/gunicorn.conf.py
xpublish_host/metrics.py
xpublish_host/utils.py
xpublish_host/examples/__init__.py
xpublish_host/examples/datasets.py
xpublish_host/examples/ds_config.yaml
xpublish_host/examples/dynamic.yaml
xpublish_host/examples/example.env
xpublish_host/examples/example.yaml
xpublish_host/loaders/__init__.py
xpublish_host/loaders/dataset.py
xpublish_host/loaders/mfdataset.py
xpublish_host/plugins/__init__.py
xpublish_host/plugins/data_points.py
xpublish_host/plugins/dconfig.py
xpublish_host-1.1.6.dist-info/LICENSE.txt
xpublish_host-1.1.6.dist-info/METADATA
xpublish_host-1.1.6.dist-info/WHEEL
xpublish_host-1.1.6.dist-info/entry_points.txt
xpublish_host-1.1.6.dist-info/top_level.txt
xpublish_host-1.1.6.dist-info/RECORD
