Metadata-Version: 2.2
Name: xpublish-host
Version: 1.1.6
Summary: A collection of tools to standardize xpublish hosting
Author-email: Kyle Wilcox <kyle@axds.co>
License: MIT License
Project-URL: Bug Tracker, https://github.com/axiom-data-science/xpublish-host/issues
Project-URL: Homepage, https://github.com/axiom-data-science/xpublish-host
Classifier: Environment :: Web Environment
Classifier: Intended Audience :: Developers
Classifier: License :: OSI Approved :: MIT License
Classifier: Operating System :: OS Independent
Classifier: Programming Language :: Python
Classifier: Programming Language :: Python :: 3 :: Only
Classifier: Programming Language :: Python :: 3.8
Classifier: Programming Language :: Python :: 3.9
Classifier: Programming Language :: Python :: 3.10
Classifier: Programming Language :: Python :: 3.11
Classifier: Topic :: Internet :: WWW/HTTP
Classifier: Topic :: Internet :: WWW/HTTP :: Dynamic Content
Requires-Python: >=3.8
License-File: LICENSE.txt
Requires-Dist: goodconf
Requires-Dist: pydantic
Requires-Dist: xpublish
